derivative/__init__.py
derivative/__version__.py
derivative/dglobal.py
derivative/differentiation.py
derivative/dlocal.py
derivative/utils.py
derivative-0.6.1.dist-info/entry_points.txt
derivative-0.6.1.dist-info/LICENSE.rst
derivative-0.6.1.dist-info/WHEEL
derivative-0.6.1.dist-info/METADATA
derivative-0.6.1.dist-info/RECORD
