Metadata-Version: 2.1
Name: derivative
Version: 0.6.1
Summary: Numerical differentiation in python.
Home-page: https://github.com/andgoldschmidt/derivative
License: MIT
Keywords: differentiation,derivative,gradient,prime
Author: Andy Goldschmidt
Author-email: andygold@uchicago.edu
Requires-Python: >=3.9,<4.0
Classifier: License :: OSI Approved :: MIT License
Classifier: Programming Language :: Python :: 3
Classifier: Programming Language :: Python :: 3.9
Classifier: Programming Language :: Python :: 3.10
Provides-Extra: dev
Provides-Extra: docs
Requires-Dist: ipykernel (>=5.2.1,<6.0.0); extra == "docs"
Requires-Dist: jupyter_client (>=6.1.3,<7.0.0); extra == "docs"
Requires-Dist: matplotlib (>=3.2.1,<4.0.0); extra == "docs"
Requires-Dist: nbsphinx (>=0.6.1,<0.7.0); extra == "docs"
Requires-Dist: numpy (>=1.18.3,<2.0.0)
Requires-Dist: pytest (>=7,<8); extra == "dev"
Requires-Dist: scikit-learn (>=1,<2)
Requires-Dist: scipy (>=1.4.1,<2.0.0)
Requires-Dist: sphinx (>=5,<6); extra == "docs"
Project-URL: Documentation, https://derivative.readthedocs.io/
Project-URL: Repository, https://github.com/andgoldschmidt/derivative
